{
  "$schema": "https://json-schema.org/draft/2020-12/schema",
  "$id": "#/components/schemas/microsoft.graph.win32LobAppMsiInformation",
  "title": "win32LobAppMsiInformation",
  "required": [
    "@odata.type"
  ],
  "type": "object",
  "properties": {
    "packageType": {
      "$ref": "#/components/schemas/microsoft.graph.win32LobAppMsiPackageType"
    },
    "productCode": {
      "type": "string",
      "description": "The MSI product code.",
      "nullable": true
    },
    "productName": {
      "type": "string",
      "description": "The MSI product name.",
      "nullable": true
    },
    "productVersion": {
      "type": "string",
      "description": "The MSI product version.",
      "nullable": true
    },
    "publisher": {
      "type": "string",
      "description": "The MSI publisher.",
      "nullable": true
    },
    "requiresReboot": {
      "type": "boolean",
      "description": "Whether the MSI app requires the machine to reboot to complete installation."
    },
    "upgradeCode": {
      "type": "string",
      "description": "The MSI upgrade code.",
      "nullable": true
    },
    "@odata.type": {
      "type": "string"
    }
  },
  "description": "Contains MSI app properties for a Win32 App."
}