{
  "$schema": "https://json-schema.org/draft/2020-12/schema",
  "$id": "#/components/schemas/microsoft.graph.scopedRoleMembership",
  "title": "microsoft.graph.scopedRoleMembership",
  "allOf": [
    {
      "$ref": "#/components/schemas/microsoft.graph.entity"
    },
    {
      "title": "scopedRoleMembership",
      "required": [
        "@odata.type"
      ],
      "type": "object",
      "properties": {
        "administrativeUnitId": {
          "type": "string",
          "description": "Unique identifier for the administrative unit that the directory role is scoped to"
        },
        "roleId": {
          "type": "string",
          "description": "Unique identifier for the directory role that the member is in."
        },
        "roleMemberInfo": {
          "$ref": "#/components/schemas/microsoft.graph.identity"
        },
        "@odata.type": {
          "type": "string"
        }
      }
    }
  ],
  "x-ms-discriminator-value": "#microsoft.graph.scopedRoleMembership"
}