{
  "$schema": "https://json-schema.org/draft/2020-12/schema",
  "$id": "#/components/schemas/microsoft.graph.placeMode",
  "title": "placeMode",
  "required": [
    "@odata.type"
  ],
  "type": "object",
  "properties": {
    "@odata.type": {
      "type": "string"
    }
  },
  "discriminator": {
    "propertyName": "@odata.type",
    "mapping": {
      "#microsoft.graph.assignedPlaceMode": "#/components/schemas/microsoft.graph.assignedPlaceMode",
      "#microsoft.graph.dropInPlaceMode": "#/components/schemas/microsoft.graph.dropInPlaceMode",
      "#microsoft.graph.reservablePlaceMode": "#/components/schemas/microsoft.graph.reservablePlaceMode"
    }
  }
}